DPTool/__init__.py
DPTool/module.py
dptool-1.0.8.dist-info/licenses/LICENSE
dptool-1.0.8.dist-info/METADATA
dptool-1.0.8.dist-info/WHEEL
dptool-1.0.8.dist-info/top_level.txt
dptool-1.0.8.dist-info/RECORD
