Metadata-Version: 2.4
Name: DPTool
Version: 1.0.8
Summary: Some scripts for Baidu SEO purpose
Home-page: 
Author: Jiayu Tan
Author-email: jtan010@uottawa.ca
Classifier: Programming Language :: Python :: 3
Classifier: License :: OSI Approved :: MIT License
Classifier: Operating System :: OS Independent
License-File: LICENSE
Requires-Dist: DrissionPage>=4.1.0
Requires-Dist: lxml>=5.3.0
Dynamic: author
Dynamic: author-email
Dynamic: classifier
Dynamic: description
Dynamic: description-content-type
Dynamic: license-file
Dynamic: requires-dist
Dynamic: summary
